<?xml version="1.0" encoding="UTF-8"?>
<launch4jConfig>
  <dontWrapJar>false</dontWrapJar>
  <headerType>gui</headerType>
  <jar>C:\Users\J.P.M\Desktop\SSD V1\SSD.jar</jar>
  <outfile>C:\Users\J.P.M\Desktop\SSD V1\SSD.exe</outfile>
  <errTitle></errTitle>
  <cmdLine></cmdLine>
  <chdir>.</chdir>
  <priority>normal</priority>
  <downloadUrl>https://www.oracle.com/java/technologies/javase/jdk21-archive-downloads.html</downloadUrl>
  <supportUrl></supportUrl>
  <stayAlive>false</stayAlive>
  <restartOnCrash>false</restartOnCrash>
  <manifest></manifest>
  <icon>C:\Users\J.P.M\Desktop\SSD V1\icons\logo.ico</icon>
  <jre>
    <path>%JAVA_HOME%;%PATH%</path>
    <requiresJdk>false</requiresJdk>
    <requires64Bit>false</requires64Bit>
    <minVersion>21.0.4</minVersion>
    <maxVersion></maxVersion>
  </jre>
</launch4jConfig>